dqp/__init__.py
dqp/disk_cache.py
dqp/disk_queue.py
dqp/py.typed
dqp/storage.py
dqp-0.1.1.dist-info/LICENSE
dqp-0.1.1.dist-info/METADATA
dqp-0.1.1.dist-info/WHEEL
dqp-0.1.1.dist-info/RECORD
