Metadata-Version: 2.1
Name: dqp
Version: 0.1.1
Summary: Cache iterator values to disk using msgpack
Home-page: https://bneijt.github.io/dqp/
License: Apache-2.0
Author: Bram Neijt
Author-email: bram@neijt.nl
Requires-Python: >=3.9,<4.0
Classifier: Intended Audience :: Developers
Classifier: License :: OSI Approved :: Apache Software License
Classifier: Programming Language :: Python :: 3
Classifier: Programming Language :: Python :: 3.9
Classifier: Programming Language :: Python :: 3.10
Classifier: Programming Language :: Python :: 3.11
Classifier: Programming Language :: Python :: 3.12
Requires-Dist: msgpack (>=1.0.7,<2.0.0)
Project-URL: Repository, https://github.com/bneijt/dqp
